Metadata-Version: 2.1
Name: wgs_analysis
Version: 0.0.7
Summary: Whole genome sequencing analysis library
